syncster/__init__.py
syncster/_version.py
syncster/crc.py
syncster/hrt.py
syncster/rbp.py
menlo_syncro-0.1.1.dist-info/COPYING.md
menlo_syncro-0.1.1.dist-info/METADATA
menlo_syncro-0.1.1.dist-info/WHEEL
menlo_syncro-0.1.1.dist-info/top_level.txt
menlo_syncro-0.1.1.dist-info/RECORD
