Metadata-Version: 2.1
Name: menlo-syncro
Version: 0.1.1
Summary: Unofficial Python framework for communication with the Menlo Syncro RRE laser synchronization unit
Author-email: Florin Boariu <florin.pt@rootshell.ro>
Project-URL: Source Code, https://gitlab.com/codedump2/syncster
Classifier: Programming Language :: Python :: 3
Classifier: License :: OSI Approved :: GNU General Public License v3 or later (GPLv3+)
Classifier: Operating System :: POSIX :: Linux
Classifier: Development Status :: 2 - Pre-Alpha
Classifier: Environment :: Console
Classifier: Intended Audience :: Science/Research
Classifier: Topic :: Scientific/Engineering
Requires-Python: >=3.8
License-File: COPYING.md
Requires-Dist: pyserial
Requires-Dist: pyyaml
Provides-Extra: test
Requires-Dist: pytest ; extra == 'test'
Requires-Dist: pytest-cov ; extra == 'test'
Requires-Dist: pytest-asyncio ; extra == 'test'
Requires-Dist: caproto ; extra == 'test'
